multithreading/__init__.py
multithreading/logger.py
multithreading/multithread.py
multithreading/multithread_request.py
multithreading/multithread_request_aria2.py
multithreading-0.2.0.dist-info/LICENSE
multithreading-0.2.0.dist-info/METADATA
multithreading-0.2.0.dist-info/WHEEL
multithreading-0.2.0.dist-info/top_level.txt
multithreading-0.2.0.dist-info/RECORD
