Metadata-Version: 2.1
Name: multithreading
Version: 0.2.0
Summary: MultiThreading: Thread + Queue
Home-page: https://github.com/aztecrabbit/multithreading
Author: aztecrabbit
Author-email: ars.xda@gmail.com
License: UNKNOWN
Platform: UNKNOWN
Classifier: Programming Language :: Python :: 3
Classifier: License :: OSI Approved :: MIT License
Classifier: Operating System :: OS Independent
Requires-Python: >=3.6
